[
  {
    "_type": "tag",
    "name": "LUA_CORE",
    "path": "C:\\Users\\JeongWooLee\\PycharmProjects\\BinCENT\\lua\\src\\lopcodes.c",
    "pattern": "/^#define LUA_CORE$/",
    "file": true,
    "language": "C",
    "line": 8,
    "kind": "macro",
    "roles": "def",
    "extras": "fileScope",
    "end": 8
  },
  {
    "_type": "tag",
    "name": "a",
    "path": "C:\\Users\\JeongWooLee\\PycharmProjects\\BinCENT\\lua\\src\\lopcodes.c",
    "pattern": "/^#define opmode(t,a,b,c,m) (((t)<<7) | ((a)<<6) | ((b)<<4) | ((c)<<2) | (m))$/",
    "language": "C",
    "line": 59,
    "kind": "macroparam",
    "scope": "opmode",
    "scopeKind": "macro",
    "roles": "def",
    "nth": 1
  },
  {
    "_type": "tag",
    "name": "b",
    "path": "C:\\Users\\JeongWooLee\\PycharmProjects\\BinCENT\\lua\\src\\lopcodes.c",
    "pattern": "/^#define opmode(t,a,b,c,m) (((t)<<7) | ((a)<<6) | ((b)<<4) | ((c)<<2) | (m))$/",
    "language": "C",
    "line": 59,
    "kind": "macroparam",
    "scope": "opmode",
    "scopeKind": "macro",
    "roles": "def",
    "nth": 2
  },
  {
    "_type": "tag",
    "name": "c",
    "path": "C:\\Users\\JeongWooLee\\PycharmProjects\\BinCENT\\lua\\src\\lopcodes.c",
    "pattern": "/^#define opmode(t,a,b,c,m) (((t)<<7) | ((a)<<6) | ((b)<<4) | ((c)<<2) | (m))$/",
    "language": "C",
    "line": 59,
    "kind": "macroparam",
    "scope": "opmode",
    "scopeKind": "macro",
    "roles": "def",
    "nth": 3
  },
  {
    "_type": "tag",
    "name": "lopcodes_c",
    "path": "C:\\Users\\JeongWooLee\\PycharmProjects\\BinCENT\\lua\\src\\lopcodes.c",
    "pattern": "/^#define lopcodes_c$/",
    "file": true,
    "language": "C",
    "line": 7,
    "kind": "macro",
    "roles": "def",
    "extras": "fileScope",
    "end": 7
  },
  {
    "_type": "tag",
    "name": "luaP_opmodes",
    "path": "C:\\Users\\JeongWooLee\\PycharmProjects\\BinCENT\\lua\\src\\lopcodes.c",
    "pattern": "/^const lu_byte luaP_opmodes[NUM_OPCODES] = {$/",
    "language": "C",
    "line": 61,
    "typeref": "typename:const lu_byte[]",
    "kind": "variable",
    "roles": "def",
    "end": 101
  },
  {
    "_type": "tag",
    "name": "luaP_opnames",
    "path": "C:\\Users\\JeongWooLee\\PycharmProjects\\BinCENT\\lua\\src\\lopcodes.c",
    "pattern": "/^const char *const luaP_opnames[NUM_OPCODES+1] = {$/",
    "language": "C",
    "line": 16,
    "typeref": "typename:const char * const[]",
    "kind": "variable",
    "roles": "def",
    "end": 56,
    "strings": [
      "MOVE",
      "LOADK",
      "LOADBOOL",
      "LOADNIL",
      "GETUPVAL",
      "GETGLOBAL",
      "GETTABLE",
      "SETGLOBAL",
      "SETUPVAL",
      "SETTABLE",
      "NEWTABLE",
      "SELF",
      "ADD",
      "SUB",
      "MUL",
      "DIV",
      "MOD",
      "POW",
      "UNM",
      "NOT",
      "LEN",
      "CONCAT",
      "JMP",
      "EQ",
      "LT",
      "LE",
      "TEST",
      "TESTSET",
      "CALL",
      "TAILCALL",
      "RETURN",
      "FORLOOP",
      "FORPREP",
      "TFORLOOP",
      "SETLIST",
      "CLOSE",
      "CLOSURE",
      "VARARG"
    ]
  },
  {
    "_type": "tag",
    "name": "m",
    "path": "C:\\Users\\JeongWooLee\\PycharmProjects\\BinCENT\\lua\\src\\lopcodes.c",
    "pattern": "/^#define opmode(t,a,b,c,m) (((t)<<7) | ((a)<<6) | ((b)<<4) | ((c)<<2) | (m))$/",
    "language": "C",
    "line": 59,
    "kind": "macroparam",
    "scope": "opmode",
    "scopeKind": "macro",
    "roles": "def",
    "nth": 4
  },
  {
    "_type": "tag",
    "name": "opmode",
    "path": "C:\\Users\\JeongWooLee\\PycharmProjects\\BinCENT\\lua\\src\\lopcodes.c",
    "pattern": "/^#define opmode(/",
    "file": true,
    "language": "C",
    "line": 59,
    "kind": "macro",
    "signature": "(t,a,b,c,m)",
    "roles": "def",
    "extras": "fileScope",
    "end": 59
  },
  {
    "_type": "tag",
    "name": "t",
    "path": "C:\\Users\\JeongWooLee\\PycharmProjects\\BinCENT\\lua\\src\\lopcodes.c",
    "pattern": "/^#define opmode(t,a,b,c,m) (((t)<<7) | ((a)<<6) | ((b)<<4) | ((c)<<2) | (m))$/",
    "language": "C",
    "line": 59,
    "kind": "macroparam",
    "scope": "opmode",
    "scopeKind": "macro",
    "roles": "def",
    "nth": 0
  }
]